odoo/addons/purchase_transport_mode/README.rst
odoo/addons/purchase_transport_mode/__init__.py
odoo/addons/purchase_transport_mode/__manifest__.py
odoo/addons/purchase_transport_mode/data/purchase_exception_data.xml
odoo/addons/purchase_transport_mode/i18n/fr.po
odoo/addons/purchase_transport_mode/i18n/it.po
odoo/addons/purchase_transport_mode/i18n/purchase_transport_mode.pot
odoo/addons/purchase_transport_mode/models/__init__.py
odoo/addons/purchase_transport_mode/models/purchase_order.py
odoo/addons/purchase_transport_mode/models/purchase_transport_mode.py
odoo/addons/purchase_transport_mode/models/purchase_transport_mode_constraint.py
odoo/addons/purchase_transport_mode/models/res_company.py
odoo/addons/purchase_transport_mode/models/res_config_settings.py
odoo/addons/purchase_transport_mode/models/res_partner.py
odoo/addons/purchase_transport_mode/readme/CONTRIBUTORS.rst
odoo/addons/purchase_transport_mode/readme/DESCRIPTION.rst
odoo/addons/purchase_transport_mode/readme/USAGE.rst
odoo/addons/purchase_transport_mode/security/ir.model.access.csv
odoo/addons/purchase_transport_mode/static/description/icon.png
odoo/addons/purchase_transport_mode/static/description/index.html
odoo/addons/purchase_transport_mode/templates/purchase_order_transport_mode_status.xml
odoo/addons/purchase_transport_mode/tests/__init__.py
odoo/addons/purchase_transport_mode/tests/test_purchase_transport_mode.py
odoo/addons/purchase_transport_mode/views/purchase_order_view.xml
odoo/addons/purchase_transport_mode/views/purchase_transport_mode_constraint_views.xml
odoo/addons/purchase_transport_mode/views/purchase_transport_mode_views.xml
odoo/addons/purchase_transport_mode/views/res_config_settings_views.xml
odoo/addons/purchase_transport_mode/views/res_partner_views.xml
odoo_addon_purchase_transport_mode-16.0.1.1.0.2.dist-info/METADATA
odoo_addon_purchase_transport_mode-16.0.1.1.0.2.dist-info/WHEEL
odoo_addon_purchase_transport_mode-16.0.1.1.0.2.dist-info/top_level.txt
odoo_addon_purchase_transport_mode-16.0.1.1.0.2.dist-info/RECORD
