Metadata-Version: 2.1
Name: odoo-addon-purchase_transport_mode
Version: 16.0.1.1.0.2
Summary: Purchase expection based on constraints
Home-page: https://github.com/OCA/purchase-workflow
Author: Camptocamp, BCIM, Odoo Community Association (OCA)
Author-email: support@odoo-community.org
License: AGPL-3
Classifier: Programming Language :: Python
Classifier: Framework :: Odoo
Classifier: Framework :: Odoo :: 16.0
Classifier: License :: OSI Approved :: GNU Affero General Public License v3
Classifier: Development Status :: 4 - Beta
Requires-Python: >=3.10
Requires-Dist: odoo-addon-purchase-exception<16.1dev,>=16.0dev
Requires-Dist: odoo<16.1dev,>=16.0a
